[{"place_id": 298785738, "licence": "Data \u00a9 OpenStreetMap contributors, ODbL 1.0. https://osm.org/copyright", "osm_type": "relation", "osm_id": 1839157, "boundingbox": ["42.2852244", "42.4271508", "-72.6391297", "-72.5315868"], "lat": "42.35637", "lon": "-72.5620883", "display_name": "Hadley, Hampshire County, Massachusetts, 01035, United States", "class": "boundary", "type": "administrative", "importance": 0.6092860936070887, "icon": "https://nominatim.openstreetmap.org/ui/mapicons/poi_boundary_administrative.p.20.png"}]